oxo_2_pkg/__init__.py
oxo_2_pkg/oxo.py
oxo_2_pkg/models/__init__.py
oxo_2_pkg/models/models.py
oxo_2_pkg/resources/__init__.py
oxo_2_pkg/resources/data.py
oxo_2_pkg/resources/version.md
oxo_2_pkg/text/__init__.py
oxo_2_pkg/text/text.py
oxo_2_pkg/utils/__init__.py
oxo_2_pkg/utils/methods.py
oxo_2_pkg-1.0.1.data/scripts/oxo-2
oxo_2_pkg-1.0.1.dist-info/LICENSE
oxo_2_pkg-1.0.1.dist-info/METADATA
oxo_2_pkg-1.0.1.dist-info/WHEEL
oxo_2_pkg-1.0.1.dist-info/top_level.txt
oxo_2_pkg-1.0.1.dist-info/RECORD
