Metadata-Version: 2.1
Name: oxo-2-pkg
Version: 1.0.1
Summary: naughts and crosses game
Home-page: https://github.com/add-harris/oxo_2_pkg
Author: Adam Harrison
Author-email: author@example.com
License: UNKNOWN
Platform: UNKNOWN
Classifier: Programming Language :: Python :: 2.7
Classifier: License :: OSI Approved :: MIT License
Classifier: Operating System :: OS Independent
Requires-Python: >=2.7
